<?xml version="1.0" encoding="UTF-8"?>
<!DOCTYPE mapper PUBLIC "-//mybatis.org//DTD Mapper 3.0//EN" "http://mybatis.org/dtd/mybatis-3-mapper.dtd">
<mapper namespace="com.woniu.gdj.mapper.SystemcouponMapper">
  <resultMap id="BaseResultMap" type="com.woniu.gdj.entity.Systemcoupon">
    <!--
      WARNING - @mbggenerated
      This element is automatically generated by MyBatis Generator, do not modify.
      This element was generated on Mon Jun 08 16:26:28 CST 2020.
    -->
    <id column="systemCouponID" jdbcType="INTEGER" property="systemcouponid" />
    <result column="couponCode" jdbcType="VARCHAR" property="couponcode" />
    <result column="couponName" jdbcType="VARCHAR" property="couponname" />
    <result column="couponMoney" jdbcType="DECIMAL" property="couponmoney" />
    <result column="couponStartDT" jdbcType="TIMESTAMP" property="couponstartdt" />
    <result column="couponEndDT" jdbcType="TIMESTAMP" property="couponenddt" />
    <result column="isUse" jdbcType="INTEGER" property="isuse" />
    <result column="useDT" jdbcType="TIMESTAMP" property="usedt" />
    <result column="useState" jdbcType="DECIMAL" property="usestate" />
    <result column="isDelete" jdbcType="INTEGER" property="isdelete" />
    <result column="theNote" jdbcType="VARCHAR" property="thenote" />
  </resultMap>
  <sql id="Example_Where_Clause">
    <!--
      WARNING - @mbggenerated
      This element is automatically generated by MyBatis Generator, do not modify.
      This element was generated on Mon Jun 08 16:26:28 CST 2020.
    -->
    <where>
      <foreach collection="oredCriteria" item="criteria" separator="or">
        <if test="criteria.valid">
          <trim prefix="(" prefixOverrides="and" suffix=")">
            <foreach collection="criteria.criteria" item="criterion">
              <choose>
                <when test="criterion.noValue">
                  and ${criterion.condition}
                </when>
                <when test="criterion.singleValue">
                  and ${criterion.condition} #{criterion.value}
                </when>
                <when test="criterion.betweenValue">
                  and ${criterion.condition} #{criterion.value} and #{criterion.secondValue}
                </when>
                <when test="criterion.listValue">
                  and ${criterion.condition}
                  <foreach close=")" collection="criterion.value" item="listItem" open="(" separator=",">
                    #{listItem}
                  </foreach>
                </when>
              </choose>
            </foreach>
          </trim>
        </if>
      </foreach>
    </where>
  </sql>
  <sql id="Update_By_Example_Where_Clause">
    <!--
      WARNING - @mbggenerated
      This element is automatically generated by MyBatis Generator, do not modify.
      This element was generated on Mon Jun 08 16:26:28 CST 2020.
    -->
    <where>
      <foreach collection="example.oredCriteria" item="criteria" separator="or">
        <if test="criteria.valid">
          <trim prefix="(" prefixOverrides="and" suffix=")">
            <foreach collection="criteria.criteria" item="criterion">
              <choose>
                <when test="criterion.noValue">
                  and ${criterion.condition}
                </when>
                <when test="criterion.singleValue">
                  and ${criterion.condition} #{criterion.value}
                </when>
                <when test="criterion.betweenValue">
                  and ${criterion.condition} #{criterion.value} and #{criterion.secondValue}
                </when>
                <when test="criterion.listValue">
                  and ${criterion.condition}
                  <foreach close=")" collection="criterion.value" item="listItem" open="(" separator=",">
                    #{listItem}
                  </foreach>
                </when>
              </choose>
            </foreach>
          </trim>
        </if>
      </foreach>
    </where>
  </sql>
  <sql id="Base_Column_List">
    <!--
      WARNING - @mbggenerated
      This element is automatically generated by MyBatis Generator, do not modify.
      This element was generated on Mon Jun 08 16:26:28 CST 2020.
    -->
    systemCouponID, couponCode, couponName, couponMoney, couponStartDT, couponEndDT, 
    isUse, useDT, useState, isDelete, theNote
  </sql>
  <select id="selectByExample" parameterType="com.woniu.gdj.entity.SystemcouponExample" resultMap="BaseResultMap">
    <!--
      WARNING - @mbggenerated
      This element is automatically generated by MyBatis Generator, do not modify.
      This element was generated on Mon Jun 08 16:26:28 CST 2020.
    -->
    select
    <if test="distinct">
      distinct
    </if>
    <include refid="Base_Column_List" />
    from systemcoupon
    <if test="_parameter != null">
      <include refid="Example_Where_Clause" />
    </if>
    <if test="orderByClause != null">
      order by ${orderByClause}
    </if>
  </select>
  <select id="selectByPrimaryKey" parameterType="java.lang.Integer" resultMap="BaseResultMap">
    <!--
      WARNING - @mbggenerated
      This element is automatically generated by MyBatis Generator, do not modify.
      This element was generated on Mon Jun 08 16:26:28 CST 2020.
    -->
    select 
    <include refid="Base_Column_List" />
    from systemcoupon
    where systemCouponID = #{systemcouponid,jdbcType=INTEGER}
  </select>
  <delete id="deleteByPrimaryKey" parameterType="java.lang.Integer">
    <!--
      WARNING - @mbggenerated
      This element is automatically generated by MyBatis Generator, do not modify.
      This element was generated on Mon Jun 08 16:26:28 CST 2020.
    -->
    delete from systemcoupon
    where systemCouponID = #{systemcouponid,jdbcType=INTEGER}
  </delete>
  <delete id="deleteByExample" parameterType="com.woniu.gdj.entity.SystemcouponExample">
    <!--
      WARNING - @mbggenerated
      This element is automatically generated by MyBatis Generator, do not modify.
      This element was generated on Mon Jun 08 16:26:28 CST 2020.
    -->
    delete from systemcoupon
    <if test="_parameter != null">
      <include refid="Example_Where_Clause" />
    </if>
  </delete>
  <insert id="insert" parameterType="com.woniu.gdj.entity.Systemcoupon">
    <!--
      WARNING - @mbggenerated
      This element is automatically generated by MyBatis Generator, do not modify.
      This element was generated on Mon Jun 08 16:26:28 CST 2020.
    -->
    insert into systemcoupon (systemCouponID, couponCode, couponName, 
      couponMoney, couponStartDT, couponEndDT, 
      isUse, useDT, useState, 
      isDelete, theNote)
    values (#{systemcouponid,jdbcType=INTEGER}, #{couponcode,jdbcType=VARCHAR}, #{couponname,jdbcType=VARCHAR}, 
      #{couponmoney,jdbcType=DECIMAL}, #{couponstartdt,jdbcType=TIMESTAMP}, #{couponenddt,jdbcType=TIMESTAMP}, 
      #{isuse,jdbcType=INTEGER}, #{usedt,jdbcType=TIMESTAMP}, #{usestate,jdbcType=DECIMAL}, 
      #{isdelete,jdbcType=INTEGER}, #{thenote,jdbcType=VARCHAR})
  </insert>
  <insert id="insertSelective" parameterType="com.woniu.gdj.entity.Systemcoupon">
    <!--
      WARNING - @mbggenerated
      This element is automatically generated by MyBatis Generator, do not modify.
      This element was generated on Mon Jun 08 16:26:28 CST 2020.
    -->
    insert into systemcoupon
    <trim prefix="(" suffix=")" suffixOverrides=",">
      <if test="systemcouponid != null">
        systemCouponID,
      </if>
      <if test="couponcode != null">
        couponCode,
      </if>
      <if test="couponname != null">
        couponName,
      </if>
      <if test="couponmoney != null">
        couponMoney,
      </if>
      <if test="couponstartdt != null">
        couponStartDT,
      </if>
      <if test="couponenddt != null">
        couponEndDT,
      </if>
      <if test="isuse != null">
        isUse,
      </if>
      <if test="usedt != null">
        useDT,
      </if>
      <if test="usestate != null">
        useState,
      </if>
      <if test="isdelete != null">
        isDelete,
      </if>
      <if test="thenote != null">
        theNote,
      </if>
    </trim>
    <trim prefix="values (" suffix=")" suffixOverrides=",">
      <if test="systemcouponid != null">
        #{systemcouponid,jdbcType=INTEGER},
      </if>
      <if test="couponcode != null">
        #{couponcode,jdbcType=VARCHAR},
      </if>
      <if test="couponname != null">
        #{couponname,jdbcType=VARCHAR},
      </if>
      <if test="couponmoney != null">
        #{couponmoney,jdbcType=DECIMAL},
      </if>
      <if test="couponstartdt != null">
        #{couponstartdt,jdbcType=TIMESTAMP},
      </if>
      <if test="couponenddt != null">
        #{couponenddt,jdbcType=TIMESTAMP},
      </if>
      <if test="isuse != null">
        #{isuse,jdbcType=INTEGER},
      </if>
      <if test="usedt != null">
        #{usedt,jdbcType=TIMESTAMP},
      </if>
      <if test="usestate != null">
        #{usestate,jdbcType=DECIMAL},
      </if>
      <if test="isdelete != null">
        #{isdelete,jdbcType=INTEGER},
      </if>
      <if test="thenote != null">
        #{thenote,jdbcType=VARCHAR},
      </if>
    </trim>
  </insert>
  <select id="countByExample" parameterType="com.woniu.gdj.entity.SystemcouponExample" resultType="java.lang.Integer">
    <!--
      WARNING - @mbggenerated
      This element is automatically generated by MyBatis Generator, do not modify.
      This element was generated on Mon Jun 08 16:26:28 CST 2020.
    -->
    select count(*) from systemcoupon
    <if test="_parameter != null">
      <include refid="Example_Where_Clause" />
    </if>
  </select>
  <update id="updateByExampleSelective" parameterType="map">
    <!--
      WARNING - @mbggenerated
      This element is automatically generated by MyBatis Generator, do not modify.
      This element was generated on Mon Jun 08 16:26:28 CST 2020.
    -->
    update systemcoupon
    <set>
      <if test="record.systemcouponid != null">
        systemCouponID = #{record.systemcouponid,jdbcType=INTEGER},
      </if>
      <if test="record.couponcode != null">
        couponCode = #{record.couponcode,jdbcType=VARCHAR},
      </if>
      <if test="record.couponname != null">
        couponName = #{record.couponname,jdbcType=VARCHAR},
      </if>
      <if test="record.couponmoney != null">
        couponMoney = #{record.couponmoney,jdbcType=DECIMAL},
      </if>
      <if test="record.couponstartdt != null">
        couponStartDT = #{record.couponstartdt,jdbcType=TIMESTAMP},
      </if>
      <if test="record.couponenddt != null">
        couponEndDT = #{record.couponenddt,jdbcType=TIMESTAMP},
      </if>
      <if test="record.isuse != null">
        isUse = #{record.isuse,jdbcType=INTEGER},
      </if>
      <if test="record.usedt != null">
        useDT = #{record.usedt,jdbcType=TIMESTAMP},
      </if>
      <if test="record.usestate != null">
        useState = #{record.usestate,jdbcType=DECIMAL},
      </if>
      <if test="record.isdelete != null">
        isDelete = #{record.isdelete,jdbcType=INTEGER},
      </if>
      <if test="record.thenote != null">
        theNote = #{record.thenote,jdbcType=VARCHAR},
      </if>
    </set>
    <if test="_parameter != null">
      <include refid="Update_By_Example_Where_Clause" />
    </if>
  </update>
  <update id="updateByExample" parameterType="map">
    <!--
      WARNING - @mbggenerated
      This element is automatically generated by MyBatis Generator, do not modify.
      This element was generated on Mon Jun 08 16:26:28 CST 2020.
    -->
    update systemcoupon
    set systemCouponID = #{record.systemcouponid,jdbcType=INTEGER},
      couponCode = #{record.couponcode,jdbcType=VARCHAR},
      couponName = #{record.couponname,jdbcType=VARCHAR},
      couponMoney = #{record.couponmoney,jdbcType=DECIMAL},
      couponStartDT = #{record.couponstartdt,jdbcType=TIMESTAMP},
      couponEndDT = #{record.couponenddt,jdbcType=TIMESTAMP},
      isUse = #{record.isuse,jdbcType=INTEGER},
      useDT = #{record.usedt,jdbcType=TIMESTAMP},
      useState = #{record.usestate,jdbcType=DECIMAL},
      isDelete = #{record.isdelete,jdbcType=INTEGER},
      theNote = #{record.thenote,jdbcType=VARCHAR}
    <if test="_parameter != null">
      <include refid="Update_By_Example_Where_Clause" />
    </if>
  </update>
  <update id="updateByPrimaryKeySelective" parameterType="com.woniu.gdj.entity.Systemcoupon">
    <!--
      WARNING - @mbggenerated
      This element is automatically generated by MyBatis Generator, do not modify.
      This element was generated on Mon Jun 08 16:26:28 CST 2020.
    -->
    update systemcoupon
    <set>
      <if test="couponcode != null">
        couponCode = #{couponcode,jdbcType=VARCHAR},
      </if>
      <if test="couponname != null">
        couponName = #{couponname,jdbcType=VARCHAR},
      </if>
      <if test="couponmoney != null">
        couponMoney = #{couponmoney,jdbcType=DECIMAL},
      </if>
      <if test="couponstartdt != null">
        couponStartDT = #{couponstartdt,jdbcType=TIMESTAMP},
      </if>
      <if test="couponenddt != null">
        couponEndDT = #{couponenddt,jdbcType=TIMESTAMP},
      </if>
      <if test="isuse != null">
        isUse = #{isuse,jdbcType=INTEGER},
      </if>
      <if test="usedt != null">
        useDT = #{usedt,jdbcType=TIMESTAMP},
      </if>
      <if test="usestate != null">
        useState = #{usestate,jdbcType=DECIMAL},
      </if>
      <if test="isdelete != null">
        isDelete = #{isdelete,jdbcType=INTEGER},
      </if>
      <if test="thenote != null">
        theNote = #{thenote,jdbcType=VARCHAR},
      </if>
    </set>
    where systemCouponID = #{systemcouponid,jdbcType=INTEGER}
  </update>
  <update id="updateByPrimaryKey" parameterType="com.woniu.gdj.entity.Systemcoupon">
    <!--
      WARNING - @mbggenerated
      This element is automatically generated by MyBatis Generator, do not modify.
      This element was generated on Mon Jun 08 16:26:28 CST 2020.
    -->
    update systemcoupon
    set couponCode = #{couponcode,jdbcType=VARCHAR},
      couponName = #{couponname,jdbcType=VARCHAR},
      couponMoney = #{couponmoney,jdbcType=DECIMAL},
      couponStartDT = #{couponstartdt,jdbcType=TIMESTAMP},
      couponEndDT = #{couponenddt,jdbcType=TIMESTAMP},
      isUse = #{isuse,jdbcType=INTEGER},
      useDT = #{usedt,jdbcType=TIMESTAMP},
      useState = #{usestate,jdbcType=DECIMAL},
      isDelete = #{isdelete,jdbcType=INTEGER},
      theNote = #{thenote,jdbcType=VARCHAR}
    where systemCouponID = #{systemcouponid,jdbcType=INTEGER}
  </update>
</mapper>